odoo10_addon_base_delivery_carrier_files-10.0.1.0.2-py3.8-nspkg.pth
odoo/addons/base_delivery_carrier_files/README.rst
odoo/addons/base_delivery_carrier_files/__init__.py
odoo/addons/base_delivery_carrier_files/__manifest__.py
odoo/addons/base_delivery_carrier_files/csv_writer/__init__.py
odoo/addons/base_delivery_carrier_files/csv_writer/unicode_writer.py
odoo/addons/base_delivery_carrier_files/demo/carrier_file_data.xml
odoo/addons/base_delivery_carrier_files/generator/__init__.py
odoo/addons/base_delivery_carrier_files/generator/base_line.py
odoo/addons/base_delivery_carrier_files/generator/file_generator.py
odoo/addons/base_delivery_carrier_files/generator/generic_generator.py
odoo/addons/base_delivery_carrier_files/i18n/am.po
odoo/addons/base_delivery_carrier_files/i18n/ar.po
odoo/addons/base_delivery_carrier_files/i18n/base_delivery_carrier_files.pot
odoo/addons/base_delivery_carrier_files/i18n/bg.po
odoo/addons/base_delivery_carrier_files/i18n/bs.po
odoo/addons/base_delivery_carrier_files/i18n/ca.po
odoo/addons/base_delivery_carrier_files/i18n/ca_ES.po
odoo/addons/base_delivery_carrier_files/i18n/cs.po
odoo/addons/base_delivery_carrier_files/i18n/da.po
odoo/addons/base_delivery_carrier_files/i18n/de.po
odoo/addons/base_delivery_carrier_files/i18n/el_GR.po
odoo/addons/base_delivery_carrier_files/i18n/en.po
odoo/addons/base_delivery_carrier_files/i18n/en_GB.po
odoo/addons/base_delivery_carrier_files/i18n/es.po
odoo/addons/base_delivery_carrier_files/i18n/es_AR.po
odoo/addons/base_delivery_carrier_files/i18n/es_CL.po
odoo/addons/base_delivery_carrier_files/i18n/es_CO.po
odoo/addons/base_delivery_carrier_files/i18n/es_CR.po
odoo/addons/base_delivery_carrier_files/i18n/es_DO.po
odoo/addons/base_delivery_carrier_files/i18n/es_EC.po
odoo/addons/base_delivery_carrier_files/i18n/es_MX.po
odoo/addons/base_delivery_carrier_files/i18n/es_PE.po
odoo/addons/base_delivery_carrier_files/i18n/es_PY.po
odoo/addons/base_delivery_carrier_files/i18n/es_VE.po
odoo10_addon_base_delivery_carrier_files-10.0.1.0.2.dist-info/METADATA
odoo10_addon_base_delivery_carrier_files-10.0.1.0.2.dist-info/WHEEL
odoo10_addon_base_delivery_carrier_files-10.0.1.0.2.dist-info/namespace_packages.txt
odoo10_addon_base_delivery_carrier_files-10.0.1.0.2.dist-info/top_level.txt
odoo10_addon_base_delivery_carrier_files-10.0.1.0.2.dist-info/RECORD
